envkey/__init__.py
envkey/constants.py
envkey/fetch.py
envkey/loader.py
envkey/ext/envkey-source_2.4.2_darwin_amd64/LICENSE
envkey/ext/envkey-source_2.4.2_darwin_amd64/README.md
envkey/ext/envkey-source_2.4.2_darwin_amd64/envkey-source
envkey/ext/envkey-source_2.4.2_darwin_amd64/envkeysource-version.txt
envkey/ext/envkey-source_2.4.2_darwin_arm64/LICENSE
envkey/ext/envkey-source_2.4.2_darwin_arm64/README.md
envkey/ext/envkey-source_2.4.2_darwin_arm64/envkey-source
envkey/ext/envkey-source_2.4.2_darwin_arm64/envkeysource-version.txt
envkey/ext/envkey-source_2.4.2_freebsd_amd64/LICENSE
envkey/ext/envkey-source_2.4.2_freebsd_amd64/README.md
envkey/ext/envkey-source_2.4.2_freebsd_amd64/envkey-source
envkey/ext/envkey-source_2.4.2_freebsd_amd64/envkeysource-version.txt
envkey/ext/envkey-source_2.4.2_freebsd_arm64/LICENSE
envkey/ext/envkey-source_2.4.2_freebsd_arm64/README.md
envkey/ext/envkey-source_2.4.2_freebsd_arm64/envkey-source
envkey/ext/envkey-source_2.4.2_freebsd_arm64/envkeysource-version.txt
envkey/ext/envkey-source_2.4.2_linux_amd64/LICENSE
envkey/ext/envkey-source_2.4.2_linux_amd64/README.md
envkey/ext/envkey-source_2.4.2_linux_amd64/envkey-source
envkey/ext/envkey-source_2.4.2_linux_amd64/envkeysource-version.txt
envkey/ext/envkey-source_2.4.2_linux_arm64/LICENSE
envkey/ext/envkey-source_2.4.2_linux_arm64/README.md
envkey/ext/envkey-source_2.4.2_linux_arm64/envkey-source
envkey/ext/envkey-source_2.4.2_linux_arm64/envkeysource-version.txt
envkey/ext/envkey-source_2.4.2_windows_amd64/LICENSE
envkey/ext/envkey-source_2.4.2_windows_amd64/README.md
envkey/ext/envkey-source_2.4.2_windows_amd64/envkey-source.exe
envkey/ext/envkey-source_2.4.2_windows_amd64/envkeysource-version.txt
envkey/ext/envkey-source_2.4.2_windows_arm64/LICENSE
envkey/ext/envkey-source_2.4.2_windows_arm64/README.md
envkey/ext/envkey-source_2.4.2_windows_arm64/envkey-source.exe
envkey/ext/envkey-source_2.4.2_windows_arm64/envkeysource-version.txt
envkey-2.4.2.dist-info/LICENSE.txt
envkey-2.4.2.dist-info/METADATA
envkey-2.4.2.dist-info/WHEEL
envkey-2.4.2.dist-info/top_level.txt
envkey-2.4.2.dist-info/RECORD
