Metadata-Version: 2.1
Name: envkey
Version: 2.4.2
Summary: EnvKey's Python library. Protect API keys and credentials. Keep configuration in sync.
Home-page: https://github.com/envkey/envkey-python
Author: EnvKey
Author-email: support@envkey.com
License: MIT
Keywords: security,secrets management,configuration management,environment variables,configuration,python
Platform: UNKNOWN
Classifier: Development Status :: 5 - Production/Stable
Classifier: Intended Audience :: Developers
Classifier: Intended Audience :: System Administrators
Classifier: License :: OSI Approved :: MIT License
Classifier: Programming Language :: Python :: 2
Classifier: Programming Language :: Python :: 3
Classifier: Topic :: Security
Classifier: Topic :: Security :: Cryptography
